project_release/__init__.py
project_release/__main__.py
project_release/cli.py
project_release/py.typed
project_release-0.0.0.dist-info/LICENSE.md
project_release-0.0.0.dist-info/METADATA
project_release-0.0.0.dist-info/WHEEL
project_release-0.0.0.dist-info/entry_points.txt
project_release-0.0.0.dist-info/top_level.txt
project_release-0.0.0.dist-info/RECORD
