Metadata-Version: 2.1
Name: project_release
Version: 0.0.0
Summary: A tool to help releasing projects.
Home-page: https://github.com/jmlemetayer/project-release
Author: Jean-Marie Lemetayer
Author-email: jeanmarie.lemetayer@gmail.com
License: MIT
Project-URL: Documentation, https://project-release.readthedocs.io
Project-URL: Issues, https://github.com/jmlemetayer/project-release/issues
Classifier: License :: OSI Approved :: MIT License
Classifier: Programming Language :: Python :: 3
Classifier: Programming Language :: Python :: 3 :: Only
Requires-Python: >=3.8
License-File: LICENSE.md
